rbnf_rts/__init__.py
rbnf_rts/bootstrap.py
rbnf_rts/exrbnf_parser.py
rbnf_rts/generator.py
rbnf_rts/lexical.py
rbnf_rts/parser_gen.py
rbnf_rts/plot.py
rbnf_rts/pprinter.py
rbnf_rts/rbnf_api.py
rbnf_rts/rbnf_linker.py
rbnf_rts/routine.py
rbnf_rts/rts.py
rbnf_rts/token.py
rbnf_rts/unparse.py
rbnf_rts/utils.py
test/__init__.py
test/bootstrap.py
test/test-exrbnf-parse.py
test/arith/__init__.py
test/arith/arith.py
test/arith/test.py
test/llvmir/__init__.py
test/llvmir/llvmir.py
test/llvmir/test.py
test/multiply/__init__.py
test/multiply/multiply.py
test/multiply/test.py
test/rbnfjson/__init__.py
test/rbnfjson/benchmark.py
test/rbnfjson/parser_generated.py
test/rbnfjson/parser_wrap.py
test/rbnfjson/test.py
test/relax_lang/__init__.py
test/relax_lang/relax.py
test/relax_lang/test.py
test/type_sig/__init__.py
test/type_sig/test.py
test/type_sig/type_sig.py
rbnf_rts-1.0.dist-info/LICENSE
rbnf_rts-1.0.dist-info/METADATA
rbnf_rts-1.0.dist-info/WHEEL
rbnf_rts-1.0.dist-info/entry_points.txt
rbnf_rts-1.0.dist-info/top_level.txt
rbnf_rts-1.0.dist-info/RECORD
