Metadata-Version: 2.1
Name: rbnf-rts
Version: 1.0
Summary: UNKNOWN
Home-page: https://github.com/thautwarm/rbnf-rts
Author: thautwarm
Author-email: twshere@outlook.com
License: mit
Platform: any
Classifier: Programming Language :: Python :: 3.6
Classifier: Programming Language :: Python :: 3.7
Classifier: Programming Language :: Python :: Implementation :: CPython
Requires-Python: >=3.6.0
Requires-Dist: prettyprinter
Requires-Dist: wisepy2
